Metadata-Version: 2.1
Name: osm2gpd
Version: 1.0.1
Summary: Scrape features from OpenStreetMaps' API and return a geopandas GeoDataFrame
Home-page: UNKNOWN
Author: Nick Hand
Maintainer: Nick Hand
Maintainer-email: nick.hand@phila.gov
License: MIT
Platform: UNKNOWN
Requires-Python: >=3.6
Provides-Extra: dev
